mem_storage/__init__.py
mem_storage/cache.py
mem_storage/s3.py
mem_storage-0.1.1.dist-info/WHEEL
mem_storage-0.1.1.dist-info/METADATA
mem_storage-0.1.1.dist-info/RECORD
