Metadata-Version: 2.3
Name: mem-storage
Version: 0.1.1
Summary: S3 client and NVMe-backed LRU cache for memrun
Author: Julian Mulla
Author-email: Julian Mulla <jmulla@gmail.com>
Requires-Dist: mem-common
Requires-Dist: aioboto3>=13.0
Requires-Dist: aiofiles>=24.0
Requires-Python: >=3.11
